newords/__init__.py
newords/discovery.py
newords/ngrams.py
newords-1.2.0.dist-info/LICENSE
newords-1.2.0.dist-info/METADATA
newords-1.2.0.dist-info/WHEEL
newords-1.2.0.dist-info/top_level.txt
newords-1.2.0.dist-info/RECORD
