Metadata-Version: 2.1
Name: newords
Version: 1.2.0
Summary: Find new words from corpus
Home-page: https://github.com/Brokenwind/nlpyutil
Author: kun, wang
Author-email: wangkun6536@gmail.com
License: MIT
Keywords: NLP,New words
Platform: UNKNOWN
Classifier: Intended Audience :: Developers
Classifier: License :: OSI Approved :: MIT License
Classifier: Operating System :: OS Independent
Classifier: Natural Language :: Chinese (Simplified)
Classifier: Natural Language :: Chinese (Traditional)
Classifier: Programming Language :: Python :: 3
Classifier: Programming Language :: Python :: 3.6
Classifier: Programming Language :: Python :: 3.7
Classifier: Topic :: Text Processing
Classifier: Topic :: Text Processing :: Indexing
Classifier: Topic :: Text Processing :: Linguistic
Requires-Dist: tqdm (>=4.27)
Requires-Dist: nlpyutil (>=0.3.0)
Requires-Dist: numpy (>=1.17)
Requires-Dist: pandas
Requires-Dist: joblib
Requires-Dist: dataclasses ; python_version < "3.7"
